swm_comments/__init__.py
swm_comments/models.py
swm_comments/py.typed
swm_comments/routers.py
swm_comments/schemas.py
swm_comments/storage/__init__.py
swm_comments/storage/azure.py
swm_comments/storage/base.py
swm_comments/storage/local.py
swm_comments/storage/s3.py
swm_comments_attachments-0.3.2.dist-info/licenses/LICENSE
swm_comments_attachments-0.3.2.dist-info/METADATA
swm_comments_attachments-0.3.2.dist-info/WHEEL
swm_comments_attachments-0.3.2.dist-info/top_level.txt
swm_comments_attachments-0.3.2.dist-info/RECORD
