Metadata-Version: 2.4
Name: swm-comments-attachments
Version: 0.3.2
Summary: Generic comments and attachments system for FastAPI applications
Author-email: SkyWide <dev@skywide.ae>
License-Expression: MIT
Project-URL: Homepage, https://github.com/khanatifk991/swm-comments-attachments
Project-URL: Repository, https://github.com/khanatifk991/swm-comments-attachments
Project-URL: Documentation, https://github.com/khanatifk991/swm-comments-attachments#readme
Keywords: fastapi,comments,attachments,azure,blob-storage
Classifier: Development Status :: 3 - Alpha
Classifier: Intended Audience :: Developers
Classifier: Programming Language :: Python :: 3
Classifier: Programming Language :: Python :: 3.11
Classifier: Programming Language :: Python :: 3.12
Classifier: Framework :: FastAPI
Requires-Python: >=3.11
License-File: LICENSE
Requires-Dist: fastapi>=0.109.0
Requires-Dist: sqlalchemy>=2.0.25
Requires-Dist: pydantic>=2.5.0
Requires-Dist: azure-storage-blob>=12.19.0
Requires-Dist: boto3>=1.34.0
Requires-Dist: python-multipart>=0.0.6
Requires-Dist: aiofiles>=23.2.1
Provides-Extra: dev
Requires-Dist: pytest>=7.4.0; extra == "dev"
Requires-Dist: pytest-asyncio>=0.21.0; extra == "dev"
Requires-Dist: pytest-cov>=4.1.0; extra == "dev"
Requires-Dist: ruff>=0.1.0; extra == "dev"
Requires-Dist: mypy>=1.7.0; extra == "dev"
Dynamic: license-file
